fingear/__init__.py
fingear/country/__init__.py
fingear/country/analytics/__init__.py
fingear/country/analytics/core.py
fingear/country/analytics/portfolio.py
fingear/country/analytics/sample.py
fingear/country/analytics/strategies.py
fingear/country/load/__init__.py
fingear/country/load/comodities.py
fingear/country/load/configs.py
fingear/country/load/core.py
fingear/country/load/currencies.py
fingear/country/load/indexes.py
fingear/country/load/inflation.py
fingear/country/load/stocks.py
fingear/country/load/utils.py
fingear/country/plot/__init__.py
fingear/country/plot/core.py
fingear/datasets/Russia/info.txt
fingear/datasets/Russia/stocks.csv
fingear/instruments/__init__.py
fingear/instruments/analize.py
fingear/instruments/bond.py
fingear/instruments/portfolio.py
fingear/load/__init__.py
fingear/load/cbrf.py
fingear/load/core.py
fingear/load/tinkoff/__init__.py
fingear/load/tinkoff/bonds.py
fingear/load/tinkoff/candle.py
fingear/load/tinkoff/div.py
fingear/load/tinkoff/instruments.py
fingear/load/tinkoff/prices.py
fingear/load/tinkoff/utils.py
fingear/load/yahoo.py
fingear/parse/__init__.py
fingear/parse/cbonds.py
fingear/parse/inflation.py
fingear/parse/selenium.py
fingear/parse/stockanalysis.py
fingear/samples/__init__.py
fingear/samples/core.py
fingear/samples/data/japan_stocks.csv
fingear/samples/data/japan_stocks.pkl
fingear/samples/data/russia_stocks.csv
fingear/samples/data/russia_stocks.pkl
fingear/samples/data/usa_stocks.csv
fingear/samples/data/usa_stocks.pkl
fingear/settings.py
fingear/smart_lab.py
fingear/sql/__init__.py
fingear/sql/cbonds.py
fingear/sql/core.py
fingear/utils/__init__.py
fingear/utils/types.py
fingear-0.5.0.dist-info/METADATA
fingear-0.5.0.dist-info/WHEEL
fingear-0.5.0.dist-info/RECORD
